pythentur/Journey.py
pythentur/Location.py
pythentur/Platform.py
pythentur/__init__.py
pythentur/nsrGet.py
pythentur/prettyTime.py
pythentur/stopPlace.py
pythentur/helpers/__init__.py
pythentur/helpers/constants.py
pythentur/helpers/decode1252.py
pythentur/helpers/post_to_api.py
pythentur/helpers/prettyTime.py
src/__init__.py
src/nsrGet.py
src/prettyTime.py
src/stopPlace.py
pythentur-0.2.0.dist-info/LICENSE
pythentur-0.2.0.dist-info/METADATA
pythentur-0.2.0.dist-info/WHEEL
pythentur-0.2.0.dist-info/top_level.txt
pythentur-0.2.0.dist-info/RECORD
