Metadata-Version: 2.1
Name: pythentur
Version: 0.2.0
Summary: Simplified data retrieval from Entur in Python
Home-page: https://kmaasrud.github.io/pythentur/
Author: Knut Magnus Aasrud
Author-email: kmaasrud@outlook.com
License: UNKNOWN
Platform: UNKNOWN
Classifier: Programming Language :: Python :: 3
Classifier: License :: OSI Approved :: MIT License
Classifier: Operating System :: OS Independent
Requires-Python: >=3.6
Requires-Dist: requests
